Metadata-Version: 1.1
Name: Poosh
Version: 0.0.1
Summary: Automatically find and update remote copies of your local Git repository.
Home-page: https://github.com/alvinwan/poosh
Author: Alvin Wan
Author-email: hi@alvinwan.com
License: BSD
Download-URL: https://github.com/alvinwan/poosh/archive/0.0.1.zip
Platform: UNKNOWN
Classifier: Topic :: Utilities
Classifier: Intended Audience :: Developers
Classifier: Programming Language :: Python :: 3
Classifier: Topic :: Software Development :: Libraries
